jfx_bridge_jeb/__init__.py
jfx_bridge_jeb/install_server.py
jfx_bridge_jeb/jfx_bridge_jeb.py
jfx_bridge_jeb/test_jfx_bridge_jeb.py
jfx_bridge_jeb/server/__init__.py
jfx_bridge_jeb/server/jfx_bridge_jeb_port.py
jfx_bridge_jeb/server/jfx_bridge_jeb_server.py
jfx_bridge_jeb/server/jfx_bridge_jeb_server_shutdown.py
jfx_bridge_jeb-0.0.2.dist-info/LICENSE
jfx_bridge_jeb-0.0.2.dist-info/METADATA
jfx_bridge_jeb-0.0.2.dist-info/WHEEL
jfx_bridge_jeb-0.0.2.dist-info/top_level.txt
jfx_bridge_jeb-0.0.2.dist-info/RECORD
