Metadata-Version: 2.1
Name: jfx-bridge-jeb
Version: 0.0.2
Summary: RPC bridge from Python to JEB Python interpreter
Home-page: https://github.com/justfoxing/jfx_bridge_jeb
Author: justfoxing
Author-email: justfoxingprojects@gmail.com
License: UNKNOWN
Platform: UNKNOWN
Classifier: Programming Language :: Python
Classifier: License :: OSI Approved :: MIT License
Classifier: Operating System :: OS Independent
Requires-Dist: jfx-bridge
